prompt_blueprint_validator/__init__.py
prompt_blueprint_validator/cli.py
prompt_blueprint_validator/schema/prompt-blueprint.schema.json
prompt_blueprint_validator-0.1.0.dist-info/METADATA
prompt_blueprint_validator-0.1.0.dist-info/WHEEL
prompt_blueprint_validator-0.1.0.dist-info/entry_points.txt
prompt_blueprint_validator-0.1.0.dist-info/top_level.txt
prompt_blueprint_validator-0.1.0.dist-info/RECORD
