Metadata-Version: 2.4
Name: prompt-blueprint-validator
Version: 0.1.0
Summary: Validate Prompt Blueprint JSON against a schema
Project-URL: Homepage, https://aigeeza.com/tools/blueprint-builder
Project-URL: Repository, https://github.com/tallwhites/prompt-blueprint-schema
Requires-Python: >=3.11
Requires-Dist: jsonschema>=4.0
